pypsatopo.py
pypsatopo-1.1.2.dist-info/METADATA
pypsatopo-1.1.2.dist-info/WHEEL
pypsatopo-1.1.2.dist-info/top_level.txt
pypsatopo-1.1.2.dist-info/RECORD
