Metadata-Version: 2.1
Name: pypsatopo
Version: 1.1.2
Summary: PyPSATopo is a tool that allows generating the topographical representation of any arbitrary PyPSA-based network
Author-email: "Energy Systems Group at Aarhus University (Denmark)" <ricardo.fernandes@mpe.au.dk>
Project-URL: Homepage, https://github.com/ricnogfer/pypsatopo
Keywords: PyPSA,power system,network,visualization,representation,topography
Classifier: Programming Language :: Python :: 3
Classifier: License :: OSI Approved :: BSD License
Classifier: Operating System :: OS Independent
Requires-Python: >=3.2
Requires-Dist: pypsa
Requires-Dist: pandas
